sometimer/__init__.py
sometimer/sometimer.py
sometimer/timer.py
sometimer/tests/__init__.py
sometimer/tests/test_timer.py
sometimer-0.1.10.dist-info/LICENSE.md
sometimer-0.1.10.dist-info/METADATA
sometimer-0.1.10.dist-info/WHEEL
sometimer-0.1.10.dist-info/top_level.txt
sometimer-0.1.10.dist-info/RECORD
