Metadata-Version: 2.1
Name: sometimer
Version: 0.1.10
Summary: Easy-to-use timer for tracking runtimes
Home-page: https://github.com/ViktorStagge/timer
Author: Viktor Stagge
Author-email: viktor.stagge@gmail.com
License: UNKNOWN
Platform: UNKNOWN
Classifier: Programming Language :: Python :: 3
Classifier: License :: OSI Approved :: Apache Software License
Classifier: Operating System :: OS Independent
